docpath/__init__.py
docpath/axis.py
docpath/docpath.py
docpath/parser.py
docpath/predicate.py
docpath-0.1.1.dist-info/DESCRIPTION.rst
docpath-0.1.1.dist-info/METADATA
docpath-0.1.1.dist-info/RECORD
docpath-0.1.1.dist-info/WHEEL
docpath-0.1.1.dist-info/metadata.json
docpath-0.1.1.dist-info/top_level.txt
test/__init__.py
test/test_axis.py
test/test_docpath.py
test/test_parser.py
test/test_predicate.py
