Metadata-Version: 2.0
Name: docpath
Version: 0.1.1
Summary: Use xpath style paths with docutils document trees.
Home-page: https://bitbucket.org/libateq/docpath
Author: David Harper
Author-email: python-packages@libateq.org
License: GPL-3
Project-URL: Bug Tracker, https://bitbucket.org/libateq/docpath/issues
Project-URL: Source Code, https://bitbucket.org/libateq/docpath
Keywords: docpath docutils sphinx xpath
Platform: any
Classifier: Development Status :: 3 - Alpha
Classifier: Intended Audience :: Developers
Classifier: Intended Audience :: System Administrators
Classifier: License :: OSI Approved :: GNU General Public License v3 or later (GPLv3+)
Classifier: Natural Language :: English
Classifier: Operating System :: OS Independent
Classifier: Programming Language :: Python :: 3
Classifier: Programming Language :: Python :: 3.5
Classifier: Programming Language :: Python :: 3.6
Classifier: Programming Language :: Python :: 3.7
Classifier: Programming Language :: Python :: 3.8
Classifier: Topic :: Documentation
Requires-Python: >=3.5
Requires-Dist: docutils (>=0.14)
Requires-Dist: simpleeval (>=0.9)
